{
  "/home/gntousakis/lya/core/tst/micro-packages/node-glob/_glob.js": {
    "*.Glob": "rw",
    "*.GlobSync": "rw",
    "*._didRealPath": "rw",
    "*._didRealpath": "rw",
    "*._emitMatch": "rx",
    "*._emitQueue": "rw",
    "*._emitQueue.length": "rw",
    "*._emitQueue.push": "rx",
    "*._emitQueue.slice": "rx",
    "*._finish": "rx",
    "*._glob": "r",
    "*._glob.charAt": "rx",
    "*._makeAbs": "rx",
    "*._mark": "rx",
    "*._process": "rx",
    "*._processGlobStar": "rx",
    "*._processGlobStar2": "rx",
    "*._processQueue": "rw",
    "*._processQueue.length": "rw",
    "*._processQueue.push": "rx",
    "*._processQueue.slice": "rx",
    "*._processReaddir": "rx",
    "*._processReaddir2": "rx",
    "*._processSimple": "rx",
    "*._processSimple2": "rx",
    "*._processing": "rw",
    "*._readdir": "rx",
    "*._readdirEntries": "rx",
    "*._readdirError": "rx",
    "*._readdirInGlobStar": "rx",
    "*._realpath": "rx",
    "*._realpathSet": "rx",
    "*._stat": "rx",
    "*._stat2": "rx",
    "*.abort": "rx",
    "*.aborted": "rw",
    "*.absolute": "r",
    "*.cache": "r",
    "*.cache.*": "rw",
    "*.charAt": "rx",
    "*.code": "r",
    "*.concat": "rx",
    "*.cwd": "r",
    "*.cwdAbs": "r",
    "*.dot": "r",
    "*.emit": "rx",
    "*.follow": "r",
    "*.forEach": "rx",
    "*.found": "r",
    "*.glob": "rw",
    "*.hasMagic": "rw",
    "*.isDirectory": "rx",
    "*.isSymbolicLink": "rx",
    "*.join": "rx",
    "*.length": "r",
    "*.mark": "r",
    "*.match": "rx",
    "*.matches": "rw",
    "*.matches.*": "rw",
    "*.matches.*.*": "rw",
    "*.matches.length": "r",
    "*.maxLength": "r",
    "*.minimatch": "r",
    "*.minimatch.negate": "r",
    "*.minimatch.set": "r",
    "*.minimatch.set.*": "r",
    "*.minimatch.set.*.*": "r",
    "*.minimatch.set.*.length": "r",
    "*.minimatch.set.length": "r",
    "*.nodir": "r",
    "*.nomount": "r",
    "*.noprocess": "rw",
    "*.on": "rx",
    "*.paused": "rw",
    "*.prototype": "r",
    "*.prototype._emitMatch": "w",
    "*.prototype._finish": "w",
    "*.prototype._makeAbs": "w",
    "*.prototype._mark": "w",
    "*.prototype._process": "w",
    "*.prototype._processGlobStar": "w",
    "*.prototype._processGlobStar2": "w",
    "*.prototype._processReaddir": "w",
    "*.prototype._processReaddir2": "w",
    "*.prototype._processSimple": "w",
    "*.prototype._processSimple2": "w",
    "*.prototype._readdir": "w",
    "*.prototype._readdirEntries": "w",
    "*.prototype._readdirError": "w",
    "*.prototype._readdirInGlobStar": "w",
    "*.prototype._realpath": "w",
    "*.prototype._realpathSet": "w",
    "*.prototype._stat": "w",
    "*.prototype._stat2": "w",
    "*.prototype.abort": "w",
    "*.prototype.pause": "w",
    "*.prototype.resume": "w",
    "*.realpath": "r",
    "*.realpathCache": "r",
    "*.replace": "rx",
    "*.root": "r",
    "*.shift": "rx",
    "*.silent": "r",
    "*.slice": "rx",
    "*.stat": "r",
    "*.statCache": "r",
    "*.statCache.*": "rw",
    "*.statCache.*.isDirectory": "rx",
    "*.strict": "r",
    "*.symlinks": "r",
    "*.symlinks.*": "rw",
    "*.sync": "rw",
    "*.syscall": "r",
    "*.test": "rx",
    "Array": "rx",
    "Array.isArray": "rx",
    "Error": "rx",
    "Error.code": "w",
    "Error.path": "w",
    "Object": "r",
    "Object.create": "rx",
    "Object.keys": "rx",
    "TypeError": "rx",
    "console": "r",
    "console.error": "rx",
    "module": "r",
    "module.exports": "w",
    "process": "r",
    "process.nextTick": "rx",
    "process.platform": "r",
    "require": "rx",
    "require('./common.js')": "ir",
    "require('./common.js').alphasort": "r",
    "require('./common.js').alphasorti": "r",
    "require('./common.js').childrenIgnored": "rx",
    "require('./common.js').finish": "rx",
    "require('./common.js').isIgnored": "rx",
    "require('./common.js').makeAbs": "rx",
    "require('./common.js').mark": "rx",
    "require('./common.js').ownProp": "rx",
    "require('./common.js').setopts": "rx",
    "require('./sync.js')": "irx",
    "require('./sync.js').GlobSync": "r",
    "require('assert')": "irx",
    "require('events')": "ir",
    "require('events').EventEmitter": "r",
    "require('fs')": "ir",
    "require('fs').lstat": "rx",
    "require('fs').readdir": "rx",
    "require('fs').stat": "rx",
    "require('fs.realpath')": "ir",
    "require('fs.realpath').realpath": "rx",
    "require('inflight')": "irx",
    "require('inherits')": "irx",
    "require('minimatch')": "ir",
    "require('minimatch').GLOBSTAR": "r",
    "require('minimatch').Minimatch": "r",
    "require('once')": "irx",
    "require('path')": "ir",
    "require('path').join": "rx",
    "require('path').resolve": "rx",
    "require('path-is-absolute')": "irx",
    "require('util')": "i",
    "undefined": "r"
  }
}
